    {
       "Pathway:Fool": {
          "0": "Fool",
          "1": "Attendant_of_Mysteries",
          "2": "Miracle_Invoker",
          "3": "Scholar_of_Yore",
          "4": "Bizarro_Sorcerer",
          "5": "Marionettist",
          "6": "Faceless",
          "7": "Magician",
          "8": "Clown",
          "9": "Seer",
         "10": "not_a_beyonder",
          "-1": "Lord_of_the_Mysteries"
       },
       "Pathway:Door": {
          "0": "Door",
          "1": "Key_of_Stars",
          "2": "Planeswalker",
          "3": "Wanderer",
          "4": "Secrets_Sorcerer",
          "5": "Traveler",
          "6": "Scribe",
          "7": "Astrologer",
          "8": "Trickmaster",
          "9": "Apprentice",
         "10": "not_a_beyonder",
          "-1": "Lord_of_the_Mysteries"
       },
       "Pathway:Error": {
          "0": "Error",
          "1": "Worm_of_Time",
          "2": "Trojan_Horse_of_Destiny",
          "3": "Mentor_of_Deceit",
          "4": "Parasite",
          "5": "Dream_Stealer",
          "6": "Prometheus",
          "7": "Cryptologist",
          "8": "Swindler",
          "9": "Marauder",
         "10": "not_a_beyonder",
          "-1": "Lord_of_the_Mysteries"
       },
       "Pathway:Hanged_Man": {
          "0": "Hanged_Man",
          "1": "Dark_Angel",
          "2": "Profane_Presbyter",
          "3": "Trinity_Templar",
          "4": "Dark_Knight",
          "5": "Shepherd",
          "6": "Rose_Bishop",
          "7": "Shadow_Ascetic",
          "8": "Listener",
          "9": "Secrets_Supplicant",
         "10": "not_a_beyonder",
          "-1": "GOD"
       },
       "Pathway:Visionary": {
          "0": "Visionary",
          "1": "Author",
          "2": "Discerner",
          "3": "Dream_Weaver",
          "4": "Manipulator",
          "5": "Dreamwalker",
          "6": "Hypnotist",
          "7": "Psychiatrist",
          "8": "Telepathist",
          "9": "Spectator",
         "10": "not_a_beyonder",
          "-1": "GOD"
       },
       "Pathway:Tyrant": {
          "0": "Tyrant",
          "1": "Thunder_God",
          "2": "Calamity",
          "3": "Sea_King",
          "4": "Cataclysmic-Interrer",
          "5": "Ocean_Songster",
          "6": "Wind-blessed",
          "7": "Seafarer",
          "8": "Folk_of_Rage",
          "9": "Sailor",
         "10": "not_a_beyonder",
          "-1": "GOD"
       },
       "Pathway:Sun": {
          "0": "Sun",
          "1": "White_Angel",
          "2": "Lightseeker",
          "3": "Justice_Mentor",
          "4": "Unshadowed",
          "5": "Priest_of_Light",
          "6": "Notary",
          "7": "Solar_High_Priest",
          "8": "Light_Supplicant",
          "9": "Bard",
         "10": "not_a_beyonder",
          "-1": "GOD"
       },
       "Pathway:White_Tower": {
          "0": "White_Tower",
          "1": "Eye_of_Omniscience",
          "2": "Wisdom_Angel",
          "3": "Cognizer",
          "4": "Prophet",
          "5": "Mysticism_Magister",
          "6": "Polymath",
          "7": "Knowledge_Keeper",
          "8": "Student_of_Ratiocination",
          "9": "Reader",
         "10": "not_a_beyonder",
          "-1": "GOD"
       },

       "Pathway:Twilight_Giant": {
          "0": "Twilight_Giant",
          "1": "Hand_of_God",
          "2": "Glory",
          "3": "Silver_Knight",
          "4": "Demon_Hunter",
          "5": "Guardian",
          "6": "Dawn_Paladin",
          "7": "Weapon_Master",
          "8": "Pugilist",
          "9": "Warrior",
         "10": "not_a_beyonder",
          "-1": "Eternal_Darkness"
       },
       "Pathway:Darkness": {
          "0": "Darkness",
          "1": "Knight_of_Misfortune",
          "2": "Servant_of_Concealment",
          "3": "Horror_Bishop",
          "4": "Night_Watcher",
          "5": "Spirit_Warlock",
          "6": "Soul_Assurer",
          "7": "Nightmare",
          "8": "Midnight_Poet",
          "9": "Sleepless",
         "10": "not_a_beyonder",
          "-1": "Eternal_Darkness"
       },
       "Pathway:Death": {
           "0": "Death",
           "1": "Pale_Emperor",
           "2": "Death_Consul",
           "3": "Ferryman",
           "4": "Undying",
           "5": "Gatekeeper",
           "6": "Spirit_Guide",
           "7": "Spirit_Medium",
           "8": "Gravedigger",
           "9": "Corpse_Collector",
          "10": "not_a_beyonder",
           "-1": "Eternal_Darkness"
       },

       "Pathway:Red_Priest": {
          "0": "Red_Priest",
          "1": "Conqueror",
          "2": "Weather_Warlock",
          "3": "War_Bishop",
          "4": "Iron-Blooded_Knight",
          "5": "Reaper",
          "6": "Conspirer",
          "7": "Pyromaniac",
          "8": "Provoker",
          "9": "Hunter",
         "10": "not_a_beyonder",
          "-1": "Scourge_of_Destruction"
       },
       "Pathway:Demoness": {
           "0": "Demoness",
           "1": "Apocalypse",
           "2": "Catastrophe",
           "3": "Unaging",
           "4": "Despair",
           "5": "Afflictions",
           "6": "Pleasure",
           "7": "Witch",
           "8": "Instigator",
           "9": "Assassin",
          "10": "not_a_beyonder",
           "-1": "Scourge_of_Destruction"
       },

       "Pathway:Paragon": {
          "0": "Paragon",
          "1": "Illuminator",
          "2": "Knowledge_Magister",
          "3": "Arcane_Scholar",
          "4": "Alchemist",
          "5": "Astronomer",
          "6": "Machinery_Specialist",
          "7": "Appraiser",
          "8": "Archaeologist",
          "9": "Savant",
         "10": "not_a_beyonder",
          "-1": "Phantom_of_Knowledge"
       },
       "Pathway:Hermit": {
           "0": "Hermit",
           "1": "Knowledge_Emperor",
           "2": "Sage",
           "3": "Clairvoyant",
           "4": "Mysticologist",
           "5": "Constellations_Master",
           "6": "Scrolls_Professor",
           "7": "Warlock",
           "8": "Melee_Scholar",
           "9": "Mystery_Pryer",
          "10": "not_a_beyonder",
           "-1": "Phantom_of_Knowledge"
       },
       "Pathway:Wheel_of_Fortune": {
           "0": "Wheel_of_Fortune",
           "1": "Snake_of_Mercury",
           "2": "Soothsayer",
           "3": "Chaoswalker",
           "4": "Misfortune Mage",
           "5": "Winner",
           "6": "Calamity_Priest",
           "7": "Lucky_One",
           "8": "Robot",
           "9": "Monster",
          "10": "not_a_beyonder",
           "-1": "Key_of_Light"
       },

       "Pathway:Moon": {
          "0": "Moon_(True Ancestor)",
          "1": "Beauty_Goddess_(Queen)",
          "2": "Life-Giver_(Duke)",
          "3": "High_Summoner_(Marquis)",
          "4": "Shaman_King_(Earl)",
          "5": "Scarlet_Scholar_(Viscount)",
          "6": "Potions_Professor_(Baron)",
          "7": "Vampire",
          "8": "Beast_Tamer",
          "9": "Apothecary",
         "10": "not_a_beyonder",
          "-1": "Goddess_of_Origin"
       },
       "Pathway:Mother": {
           "0": "Mother",
           "1": "Naturewalker",
           "2": "Desolate Matriarch",
           "3": "Pallbearer",
           "4": "Ancient_Metallurgist",
           "5": "Druid",
           "6": "Biologist",
           "7": "Harvest_Priest",
           "8": "Doctor",
           "9": "Planter",
          "10": "not_a_beyonder",
           "-1": "Goddess_of_Origin"
       },

       "Pathway:Justiciar": {
          "0": "Justiciar",
          "1": "Hand_of_Order",
          "2": "Balancer",
          "3": "Chaos_Hunter",
          "4": "Imperative_Mage",
          "5": "Discipline_Paladin",
          "6": "Judge",
          "7": "Interrogator",
          "8": "Sheriff",
          "9": "Arbiter",
         "10": "not_a_beyonder",
          "-1": "The_Anarchy"
       },
       "Pathway:Black_Emperor": {
           "0": "Black_Emperor",
           "1": "Prince_of_Abolition",
           "2": "Duke_of_Entropy",
           "3": "Frenzied_Mage",
           "4": "Earl_of_the_Fallen",
           "5": "Mentor_of_Disorder",
           "6": "Baron_of_Corruption",
           "7": "Briber",
           "8": "Barbarian",
           "9": "Lawyer",
          "10": "not_a_beyonder",
           "-1": "The_Anarchy"
       },
       "Pathway:Chained": {
          "0": "Chained",
          "1": "Abomination",
          "2": "Ancient_Bane",
          "3": "Disciple_of_Silence",
          "4": "Puppet",
          "5": "Wraith",
          "6": "Zombie",
          "7": "Werewolf",
          "8": "Lunatic",
          "9": "Prisoner",
         "10": "not_a_beyonder",
          "-1": "Father_of_Devils"
       },
       "Pathway:Abyss": {
          "0": "Abyss",
          "1": "Filthy_Monarch",
          "2": "Bloody_Archduke",
          "3": "Blatherer",
          "4": "Demon",
          "5": "Desire_Apostle",
          "6": "Devil",
          "7": "Serial_Killer",
          "8": "Unwinged_Angel",
          "9": "Criminal",
         "10": "not_a_beyonder",
          "-1": "Father_of_Devils"
       }
}